{ 
         "titlede":"Sandys Rakete",
         "titleen":"Sandy&#039;s Rocket",
         "description":"Sandy ganzer Stolz ist eine neue Rakete, mit der sie einen Trip zum Mond plant. Natürlich können SpongeBob und Patrick ihre Neugier nicht bezähmen und starten die Rakete, als sie heimlich an ihr herumdoktern.",
         "links":[
                {
                        "hoster":"PutLocker",
                        "part":1,
                        "link":"4799C7F5922C8101"
                }
       ]
}