{ 
         "titlede":"Homie der Clown",
         "titleen":"Homie the Clown",
         "description":"Krusty hat Wettschulden. Um seine Einnahmen zu erhöhen, gründet er ein College für Clowns. Auch Homer besucht diese Lehranstalt. Und Papa Simpson macht sich ganz gut als Krusty-Double. So gut, dass die Mafia ihn für den echten Krusty hält...",
         "links":[
                {
                        "hoster":"PutLocker",
                        "part":1,
                        "link":"D44995E4B1BBF642"
                },{
                        "hoster":"DivxStage",
                        "part":1,
                        "link":"63ad3e80d81db"
                }
       ]
}