{ 
         "titlede":"Die Hunde Allergie",
         "titleen":"The One Where Chandler Doesn&#039;t Like Dogs",
         "description":"Phoebe hat zurzeit einen Hund in Pflege und setzt alles daran, ihn vor Chandler zu verstecken. Denn dieser hat, nach eigener Aussage, eine starke Allergie gegen Hundehaare. Doch bald schon fliegt auf, dass Chandler Hunde einfach nicht ausstehen kann ... Rachel hat ihren Assistenten Tag zum Thanksgiving-Essen eingeladen. Während des Abends gesteht Tag, dass er von seiner Freundin verlassen wurde. Da wittert Rachel ihre große Chance ...",
         "links":[
                {
                        "hoster":"PutLocker",
                        "part":1,
                        "link":"DFA8F9686ED76083"
                },{
                        "hoster":"DivxStage",
                        "part":1,
                        "link":"6uuroxpl8h0hn"
                }
       ]
}