{ 
         "titlede":"Palo Mayombe",
         "titleen":"Corazon",
         "description":"Das BAU Team reist nach Miami, um eine Reihe von mutmaßlichen Ritualmorden aufzuklären. Reid leidet derweil an Kopfschmerzen und starker Lichtempfindlichkeit. Zudem hat er Halluzinationen.",
         "links":[
                {
                        "hoster":"PutLocker",
                        "part":1,
                        "link":"D06A71B31D8533B7"
                },{
                        "hoster":"DivxStage",
                        "part":1,
                        "link":"cqou2rlq1s2kc"
                }
       ]
}