{ 
         "titlede":"Unruhe",
         "titleen":"Unruhe",
         "description":"Diesmal sind Mulder und Scully einem geisteskranken Kidnapper auf der Spur. Dieser hat vor Jahren seinen Vater umgebracht, um seine Schwester vor ihm zu schützen. Nun will er seinen Opfern &quot;helfen&quot;, indem er ihnen durch eine Operation die seelische &quot;Unruhe&quot; nimmt. Außerdem besitzt er offenbar die Fähigkeit, so genannte Gedankenfotos zu machen. Als Scully das nächste Opfer des Psychopathen wird, gerät sie in höchste Lebensgefahr. Mulder kann sie in letzter Sekunde retten ... ",
         "links":[
                {
                        "hoster":"PutLocker",
                        "part":1,
                        "link":"27A8EB1D07037F4B"
                },{
                        "hoster":"RapidVideo",
                        "part":1,
                        "link":"9lsehpqs"
                }
       ]
}