{ 
         "titlede":"Professor trifft Studentin",
         "titleen":"The One Where Ross Dates A Student",
         "description":"Rachel und Phoebe müssen für kurze Zeit ausziehen, da es in ihrer Wohnung gebrannt hat. Rachel zieht zu Joey, wo sie sich mit dem Chaos in der Wohnung anfreunden muss. Schwerer jedoch hat es Phoebe, denn sie ist zu Monica gezogen und wird dort mit deren Ordnungswahn konfrontiert ... Ross verstößt währenddessen gegen ein eisernes Gebot und lässt sich auf eine Affäre mit einer Studentin ein. Chandler muss derweilen für Joey den Kontakt zu einer Ex-Freundin herstellen ...",
         "links":[
                {
                        "hoster":"PutLocker",
                        "part":1,
                        "link":"0F6BE3C5C2D24FB4"
                },{
                        "hoster":"DivxStage",
                        "part":1,
                        "link":"5wiiiih7ax3nd"
                }
       ]
}