{ 
         "titlede":"Ein höheres Ziel",
         "titleen":"The Greater Good (a.k.a. Sides)",
         "description":"Trotz Jacks intensiven Einsatzes stirbt Boone an seinen Verletzungen. Kurz darauf kehrt Locke zurück und will sein Verschwinden sowie Boones Tod erklären. Doch Shannon schenkt ihm keinen Glauben und bittet Sayid, ihren Bruder zu rächen. Auf dem Weg zur Unglücksstelle, wo sich auch die geheimnisvolle Luke befindet, versucht Sayid, die Wahrheit aus Locke zu pressen. Indes verschwindet einer der Revolver, und Sawyer erweist sich überraschend als ein ausgezeichneter Babysitter ...",
         "links":[
                {
                        "hoster":"PutLocker",
                        "part":1,
                        "link":"EE147CE685500395"
                },{
                        "hoster":"DivxStage",
                        "part":1,
                        "link":"rpv1o8y4ju0jo"
                }
       ]
}