{ 
         "titlede":"Der Rattenfänger",
         "titleen":"Pied Piper",
         "description":"Zu Beginn ihrer Karriere als Staatsanwältin klagte Zoe Landau, die jetzige Exfrau von Cal Lightman, den jungen Jason Wilkie an. Ihm wurde vorgeworfen, den damals achtjährigen Rex Sharadon entführt und anschließend ermordet zu haben. Zwar hatte Jason die Tat nie gestanden, doch aufgrund der erdrückenden Beweislage wurde er schließlich zu Tode verurteilt. Nach 17 Jahren Haft in der Todeszelle steht nun die Vollstreckung kurz bevor. Auch Zoe und Cal, der damals als Sachverständiger den Prozess unterstützt hatte und das Todesurteil gegen Jason Wilkie befürwortete, sind zur Hinrichtung gekommen. Als Jason seine letzten Worte spricht und abermals betont, dass nicht er, sondern der sogenannte &#039;Rattenfänger&#039; den kleinen Rex umgebracht habe, liest Cal in seinem Gesichtsausdruck, dass er die Wahrheit sagt. Doch ist es tatsächlich möglich, dass Cal sich in seiner damaligen Diagnose geirrt hat?",
         "links":[
                {
                        "hoster":"PutLocker",
                        "part":1,
                        "link":"E72837D215680303"
                },{
                        "hoster":"Sockshare",
                        "part":1,
                        "link":"AC519B91DE8C8D04"
                },{
                        "hoster":"DivxStage",
                        "part":1,
                        "link":"95bk4wroguhi8"
                },{
                        "hoster":"RapidVideo",
                        "part":1,
                        "link":"kle0xj9p"
                }
       ]
}