{ 
         "titlede":"Das Geheimnis der Mumie",
         "titleen":"Inca Mummy Girl",
         "description":"Buffy und ihre Freunde besichtigen mit ihrer Klasse bei einem Museumsbesuch die Mumie einer Inka-Prinzessin. Plötzlich verschwindet ein Schüler und wird kurz darauf als Mumie in dem Sarkophag gefunden. Buffy erwartet unterdessen die Austauschschülerin Ampata aus Südamerika - nicht ahnend, dass es sich bei dem Mädchen um die Mumie aus dem Museum handelt. Sie ist ins Leben zurückgekehrt, indem sie anderen buchstäblich den Lebenshauch aussaugt.",
         "links":[
                {
                        "hoster":"RapidVideo",
                        "part":1,
                        "link":"blcjnz19"
                }
       ]
}