{ 
         "titlede":"Homer und Moe St. Cool",
         "titleen":"Homer the Moe",
         "description":"Moe erhält von seinem alten Professor den Rat, seine Kneipe einer Generalsanierung zu unterziehen. Tatsächlich macht Moe aus dem heruntergekommenen Schuppen eine exklusive Bar. Homer und seine Freunde fühlen sich dort nicht länger wohl und verlegen ihre Trinkgelage in Homers Garage. Kurze Zeit später entdeckt Moe, dass dies nicht seine Welt ist und versucht alles wieder rückgängig zu machen",
         "links":[
                {
                        "hoster":"PutLocker",
                        "part":1,
                        "link":"0BD7CC81B29A5D76"
                },{
                        "hoster":"DivxStage",
                        "part":1,
                        "link":"9ad76866799bf"
                },{
                        "hoster":"RapidVideo",
                        "part":1,
                        "link":"xdfmrh8g"
                }
       ]
}