{ 
         "titlede":"Alle Wege führen zum Du",
         "titleen":"",
         "description":"In einem Waldstück wird die Leiche von Silke Hansen gefunden. Sie hat mit ihrem Mann Erik und ihrem 17-jährigen Sohn Rasmus an einem Wochenendseminar des Paarcoaches Bernd Neumeister teilgenommen. Mick ist völlig verwirrt, als ihm und Andreas in Neumeisters Villa plötzlich seine Therapeutin Tanja gegenübersteht! Sie leitet das Seminar zusammen mit Neumeister und macht sich große Vorwürfe, vielleicht etwas Entscheidendes bei Familie Hansen übersehen zu haben...",
         "links":[
                {
                        "hoster":"PutLocker",
                        "part":1,
                        "link":"ED8C3C081F79C52A"
                }
       ]
}