{ 
         "titlede":"Einer flog in das Kuckucksnest (1)",
         "titleen":"Broken (1)",
         "description":"Um wieder Tritt zu fassen, will House mit professioneller Hilfe gegen seine Tablettensucht ankämpfen. Er checkt in der Mayfield Klinik ein, im Glauben, nach erfolgreichem Entzug ein freier Mann zu sein. Doch Anstaltsleiter Nolan will House erst dann wieder auf Patienten loslassen, wenn er sich einer umfassenden Therapie unterzogen hat. Nolan ist überzeugt, dass House&#039; Wahnzustände nicht von seinem Vicodin-Missbrauch herrühren. Er vermutet eine tiefere, psychische Störung dahinter.",
         "links":[
                {
                        "hoster":"PutLocker",
                        "part":1,
                        "link":"8619FF32DA6C537A"
                },{
                        "hoster":"Sockshare",
                        "part":1,
                        "link":"5630BDCB6B8704CC"
                },{
                        "hoster":"RapidVideo",
                        "part":1,
                        "link":"atnf3zf8"
                },{
                        "hoster":"BitShare",
                        "part":1,
                        "link":"9y6mbsi5/dr.house.s06e01.avi.html"
                },{
                        "hoster":"VideoWeed",
                        "part":1,
                        "link":"396bjnn3u8qw5"
                },{
                        "hoster":"UploadC",
                        "part":1,
                        "link":"s0lp625n2ia3/Dr.House.S06E01.Einer.flog.in.das.Kuckucksnest.Teil.1.German.WS.DVDRip.XviD-DELiCiOUS_-_kinox.to.avi.html"
                }
       ]
}