{ 
         "titlede":"Der Trickbetrüger",
         "titleen":"Episode 049",
         "description":"Noch keine Beschreibung verfügbar.",
         "links":[
                {
                        "hoster":"MyVideo",
                        "part":1,
                        "link":"2711320/Pokemon_Folge_49_Der_Trickbetrueger_1_2"
                },{
                        "hoster":"MyVideo",
                        "part":2,
                        "link":"2711394/Pokemon_Folge_49_Der_Trickbetrueger_2_2"
                },{
                        "hoster":"Sockshare",
                        "part":1,
                        "link":"1C238BD899461AB9"
                }
       ]
}