{ 
         "titlede":"Blind Dates",
         "titleen":"The One With The Blind Dates",
         "description":"Rachel und Ross sollten wieder zusammen sein - das finden zumindest Phoebe und Joey. Nachdem die beiden aber niemals von allein wieder ein Paar werden würden, beschließen die Freunde, ein wenig nachzuhelfen. Phoebe vermittelt Rachel ein Date mit einem absoluten Loser, während Joey dafür sorgt, dass Ross von seinem Blind Date versetzt wird. Als Rachel und Ross herausfinden, was ihre Freunde getan haben, setzen sich die beiden zusammen und planen einen Racheakt ...",
         "links":[
                {
                        "hoster":"PutLocker",
                        "part":1,
                        "link":"F303D2DD33673D2A"
                },{
                        "hoster":"DivxStage",
                        "part":1,
                        "link":"omxt465e16lcz"
                }
       ]
}