{ 
         "titlede":"Carpenter Street",
         "titleen":"Carpenter Street",
         "description":"Die Xindi haben einen menschlichen Agenten auf der Erde, mit Namen Loomis, den sie gezwungen haben ihnen bei ihrem Maserplan zu helfen. Unter dem Einfluss der Xindi und der Tarnung einer Blutbank beliefert Loomis die Xindi regelmäßig mit menschlichen Körpern. Es ist nun an Archer und T&#039;Pol die Xindi von der Infiltration des 21. Jahrhunderts abzuhalten...",
         "links":[
                ,
         "links":[
       ]
}