{ 
         "titlede":"Schneechaos",
         "titleen":"Love and War and Snow",
         "description":"Wegen eines angekündigten Schneesturms strandet Rory im Haus ihrer Großeltern. Diese erfahren durch ihre Enkelin, dass auch eine Tiefkühlpizza eine delikate Gaumenfreude sein kann. Max und Lorelai verbringen einen romantischen Abend. Zu Hause angekommen sind die beiden überrascht, Lane gegenüber zu stehen. Das Mädchen wartet vergeblich auf Rory, um sich ein Leid von der Seele zu sprechen.",
         "links":[
                ,
         "links":[
       ]
}