{ 
         "titlede":"Die Kinder bleiben im Bilde",
         "titleen":"The Kids Stay in the Picture",
         "description":"Noch keine Beschreibung verfügbar.",
         "links":[
                {
                        "hoster":"PutLocker",
                        "part":1,
                        "link":"F2392833F38A9C2E"
                },{
                        "hoster":"Sockshare",
                        "part":1,
                        "link":"362836273E2FAF32"
                },{
                        "hoster":"DivxStage",
                        "part":1,
                        "link":"5jbya9ebsxfo7"
                },{
                        "hoster":"BitShare",
                        "part":1,
                        "link":"01osm5sm/Gossip.Girl.S04E18.German.Dubbed.DVDRip.XviD-MiRAMAX.avi.html"
                },{
                        "hoster":"VideoWeed",
                        "part":1,
                        "link":"upt7gm8oxxud7"
                },{
                        "hoster":"UploadC",
                        "part":1,
                        "link":"oxe1ozyz7t50/Gossip.Girl.S04E18.German.Dubbed.DVDRip.XviD-MiRAMAX-stream-kinox.to.avi.html"
                }
       ]
}