{ 
         "titlede":"Brian zieht aus",
         "titleen":"Still Seceding",
         "description":"Brian erhält durch seine außergewöhnlichen Leistungen in Mathematik die Möglichkeit, an einem Mathekurs der Universität teilzunehmen. Alle sind begeistert. Doch als er eines Abends erst um ein Uhr nachts wieder nach Hause kommt, reagieren die Eltern äußerst autoritär. Dabei hat er nur mit einigen Kursteilnehmern etwas Musik gemacht. Brian hat genug von der Bevormundung durch Bill und Judy und zieht mit seinen ganzen Sachen in die Garage",
         "links":[
                {
                        "hoster":"YouTube",
                        "part":1,
                        "link":"=MP4m4aC2pIg"
                },{
                        "hoster":"YouTube",
                        "part":2,
                        "link":"=nxcwziZ2Mtg"
                }
       ]
}