{ 
         "titlede":"Anwalt entlaufen!",
         "titleen":"Change of Course",
         "description":"Seniorpartner Edwin Poole flieht aus der Nervenheilanstalt, um die Pflichtverteidigung für einen jungen Mann zu übernehmen, der des Polizistenmordes beschuldigt wird. Da Lori Colson früher als Staatsanwältin gearbeitet hat, überredet Brad Chase sie dazu, Edwin bei seinem Mordprozess mit ihrem reichen Erfahrungsschatz beizustehen. Wird Pooles lädiertes Nervenkostüm der Belastung durch die Verhandlung gewachsen sein?Paul Lewiston betraut Alan Shore mit dem Auftrag, eine ihrer wichtigsten Klientinnen vor der Verurteilung wegen Diebstahls zu bewahren. Doch um die Frau zu entlasten, muss Alan zu unsauberen Mitteln greifen. Dabei bittet er Sally um Hilfe - und stellt ihre Beziehung auf eine harte Belastungsprobe.",
         "links":[
                {
                        "hoster":"PutLocker",
                        "part":1,
                        "link":"CBD9E8F7310DAB1A"
                }
       ]
}