{ 
         "titlede":"Kal-El von Krypton",
         "titleen":"Rosetta",
         "description":"Clark entdeckt in der Indianerhöhle eine achteckige Öffnung. Offenbar das Gegenstück für ein gleichgeformtes Metallteil aus dem Raumschiff. Als Clark die beiden Teile zusammensetzt, fällt er in eine tiefe Ohnmacht, aus der er, durch neue Erkenntnisse und Fähigkeiten bereichert, erwacht. Wenig später erhält Clark E-Mails von Dr. Swann, einem geheimnisvollen Milliardär, der auf der Suche nach außerirdischem Leben ist. Dr. Swann behauptet, etwas über Clarks Herkunft zu wissen.",
         "links":[
                {
                        "hoster":"PutLocker",
                        "part":1,
                        "link":"E8AA8EFFE2E90A51"
                }
       ]
}