{ 
         "titlede":"Das Feiertagsspektakel",
         "titleen":"Holiday Spectacular",
         "description":"Diese Episode bestehet aus drei kürzeren Geschichten, die die verschiedenen  Feiertagsbräuche am Jahresende behandeln. Die erste Geschichte dreht sich um Xmas, also der Form des Weihnachtsfest, wie es im 30. Jahrhundert gefeiert wird. Der Tannenbaum, der als ausgerottet galt, wird wieder entdeckt. Er wird wieder großflächig gepflanzt, doch sorgt er im Handlungsverlauf nur für Unheil, da seine Ausbreitung außer Kontrolle gerät. Die zweite Geschichte spielt im Roboter-Glauben. Es geht um das Fest ?Robanukah?, das von Bender erfunden wird, damit dieser nicht arbeiten muss. Bender lässt die Planet-Express-Mannschaft nach fossilen Brennstoffen suchen, die im 30. Jahrhundert nicht mehr existent sind. Die dritte Geschichte erzählt eine Geschichte rund um das Kwanzaa-Fest. Um die dafür benötigten Bienenwachs-Kerzen zu ergattern, begibt sich die Crew in einen Bienenstock, in dem gewaltige Tiere leben.",
         "links":[
                {
                        "hoster":"PutLocker",
                        "part":1,
                        "link":"4458B46E50F98D92"
                },{
                        "hoster":"DivxStage",
                        "part":1,
                        "link":"2b2c9a20f2b79"
                }
       ]
}