{ 
         "titlede":"Die Qualen des Tantalus",
         "titleen":"The Torment of Tantalus",
         "description":"In Filmaufnahmen aus dem Jahre 1945 entdecken Daniel und O&#039;Neill, dass das Stargate schon früher einmal aktiv war. Catherine Langfords ehemaliger Verlobter Ernest Littlefield passierte damals das Tor und ist offenbar bis heute nicht zurückgekehrt. Daniel sucht seine alte Freundin Catherine auf, um sie zu den Vorfällen zu befragen.",
         "links":[
                {
                        "hoster":"PutLocker",
                        "part":1,
                        "link":"18C70F6823E00878"
                },{
                        "hoster":"Sockshare",
                        "part":1,
                        "link":"7BCCC811180F219F"
                },{
                        "hoster":"DivxStage",
                        "part":1,
                        "link":"ns5bt92v7uaeb"
                }
       ]
}