{ 
         "titlede":"Blutsbande, Teil 2 ",
         "titleen":"The Dragon House (2) ",
         "description":"Jarods Bruder Kyle wird von Mr. Raines im &quot;Center&quot; als Geisel gefangen gehalten. Jarod setzt alles auf eine Karte und bricht dort ein, um ihn zu befreien. Anschließend tauchen die Brüder auf der Farm von Harriet Tashman unter, die schon Jarods Eltern Margaret und Charles versteckt hat, als sie 1969 auf der Flucht vor dem &quot;Center&quot; und auf der Suche nach ihren Kindern waren.Als das FBI die Farm stürmt, kann Jarod entkommen, Kyle wird bei einer Explosion getötet. Seine Eltern und seine Schwester Emily kann der Pretender in letzter Sekunde vor einem Anschlag warnen.",
         "links":[
                ,
         "links":[
       ]
}