{ 
         "titlede":"Miss Faltblatt",
         "titleen":"Desperately seeking Miss October",
         "description":"Noch keine Beschreibung verfügbar.",
         "links":[
                {
                        "hoster":"YouTube",
                        "part":1,
                        "link":"=GQI55_I47No"
                },{
                        "hoster":"YouTube",
                        "part":2,
                        "link":"=zosfdV7liDM"
                },{
                        "hoster":"YouTube",
                        "part":3,
                        "link":"=WOSkDqoEiBY"
                }
       ]
}