{ 
         "titlede":"Bauchfreie Zone",
         "titleen":"Tank Heaven",
         "description":"Carrie möchte unbedingt gut bei ihren neuen Kollegen ankommen, doch Doug findet diese Leute total langweilig. Er tut alles, um sich bei ihnen unbeliebt zu machen und benimmt sich mit Absicht unmöglich - für Carrie natürlich der reinste Horror ... Spence und Danny haben unterdessen eine glorreiche Idee, wie sie Frauen auf sich aufmerksam machen können: Sie wollen ihre soziale Ader demonstrieren, indem sie sich um alte Leute kümmern, und als Versuchsobjekt wählen sie Arthur aus ...",
         "links":[
                {
                        "hoster":"YouTube",
                        "part":1,
                        "link":"=X7USgN9Cc-M"
                },{
                        "hoster":"MyVideo",
                        "part":1,
                        "link":"7006227/King_of_Queens_6_Staffel_Folge_21_Part_1"
                },{
                        "hoster":"MyVideo",
                        "part":2,
                        "link":"7006284/King_of_Queens_6_Staffel_Folge_21_Part_2"
                },{
                        "hoster":"PutLocker",
                        "part":1,
                        "link":"7D32B3BFBA4FF56B"
                }
       ]
}