{ 
         "titlede":"Abrechnung - Teil 1",
         "titleen":"Citizen Joe",
         "description":"Im Kampf gegen die Goa&#039;uld führen Teal&#039;c und Bra&#039;tac die Jaffa-Rebellion an. Doch Replikatoren stürmen das Rebellenschiff. Während Daniel weggebeamt wird, bringt sich die restliche Besatzung in Sicherheit. Um die desillusionierten Jaffa zu motivieren, entscheidet sich Teal&#039;c, einen Tempel der Goa&#039;uld anzugreifen. Carter macht sich Sorgen um Daniel und vermutet, dass dieser entführt wurde, da die Replikatoren Informationen über die ihnen gefährlichen Antikerwaffen erhalten wollen.",
         "links":[
                ,
         "links":[
       ]
}