{ 
         "titlede":"Juniors Traumauto",
         "titleen":"Jr. Gets His License",
         "description":"Endlich ist es so weit: Junior hat den Führerschein. Aus Angst, dass der Fahranfänger die Familienautos zu Schrott fahren könnte, hat Michael vorgesorgt. In einem Gebrauchtwagenmarkt hat er einen Honda ausgesucht, den Junior nur noch abholen muss. Michael ist ziemlich schockiert, als Junior nicht mit dem Honda, sondern mit einem uralten Wagen nach Hause kommt. Doch das qualmende Ungetüm erinnert ihn an sein erstes Auto, die gute &quot;Trudy&quot; - und der Ärger ist vergessen ...",
         "links":[
                {
                        "hoster":"YouTube",
                        "part":1,
                        "link":"=6xDsjYNeGqs"
                },{
                        "hoster":"YouTube",
                        "part":2,
                        "link":"=7GoP95XsZKU"
                },{
                        "hoster":"PutLocker",
                        "part":1,
                        "link":"45568A5AD441B7DF"
                },{
                        "hoster":"RapidVideo",
                        "part":1,
                        "link":"os4flx28"
                }
       ]
}