{ 
         "titlede":"Wer braucht schon Regeln",
         "titleen":"No Rules",
         "description":"Junior, Claire und Kady haben es satt, sich ständig an die unzähligen Regeln ihres Vaters halten zu müssen. Als sie einen Familienaufstand planen, um seiner Tyrannei ein Ende zu setzen, schlägt ihnen Michael etwas vor: Er bietet an, sieben Tage lang alle Regeln außer Kraft zu setzen und abzuwarten, was passiert. Sollten die drei die ganze Woche ohne seine Hilfe überstehen, werden die Regeln auf ewig ungültig. Geht der Versuch jedoch daneben, fordert Michael Genugtuung ...",
         "links":[
                {
                        "hoster":"YouTube",
                        "part":1,
                        "link":"=Te7plQymQBE"
                },{
                        "hoster":"YouTube",
                        "part":2,
                        "link":"=6Y2VutIBJZU"
                },{
                        "hoster":"PutLocker",
                        "part":1,
                        "link":"D86A5DC2E55D05B7"
                },{
                        "hoster":"RapidVideo",
                        "part":1,
                        "link":"lafbge28"
                }
       ]
}