{ 
         "titlede":"Marge als Seelsorgerin",
         "titleen":"In Marge We Trust",
         "description":"Marge hilft Reverend Lovejoy bei der Gemeindearbeit und gibt Einwohnern, die anrufen, gute Ratschläge. Sie bringt jedoch auch einige Anrufer in Schwierigkeiten - Unter anderem auch Ned Flanders, als er in ein Paviangehege landet.Und Homer findet auf dem Müllplatz eine japanische Waschpulverschachtel mit seinem Gesicht drauf",
         "links":[
                {
                        "hoster":"DivxStage",
                        "part":1,
                        "link":"bd0d920022205"
                },{
                        "hoster":"RapidVideo",
                        "part":1,
                        "link":"qwmgxmox"
                }
       ]
}