{ 
         "titlede":"Die anatolische Fliege",
         "titleen":"",
         "description":"Biene ist sauer auf Atze, weil er ihrer Ansicht nach immer nur an sich selbst denkt und nicht wirklich zuhört. Als Atze ihr dann auch noch ein Vorstellungsgespräch in einem Nobel-Restaurant vermasselt, lässt Biene Atze nicht mehr ran. Nun weiß der selbstbewusste Kiosk-Besitzer plötzlich nicht mehr weiter - doch glücklicherweise kommt ihm nach langem Nachdenken schließlich doch noch eine Idee: Er probiert es mit der &#039;Anatolischen Fliege&#039;, einem Aphrodisiakum, das Murat von seinem Onkel zum Verkauf bekommen hat. Harry hat das Mittel bereits ausprobiert und weiß Wunderdinge über die Wirkung zu berichten. Atze versetzt kurzerhand ein Getränk von Biene mit der dreifachen Menge der empfohlenen Dosis - nur um wenig später festzustellen, das Biene spurlos verschwunden ist. Als Atze erfährt, dass seine mit der &#039;Anatolischen Fliege&#039; voll gepumpte Freundin kurzfristig doch noch zum Vorstellungsgespräch mit ihrem potenziellen neuen Arbeitgeber - einem attraktiven Herrn - gegangen ist, läuten bei ihm plötzlich alle Alarmglocken ...",
         "links":[
                {
                        "hoster":"PutLocker",
                        "part":1,
                        "link":"54021A39D72F9073"
                }
       ]
}