{ 
         "titlede":"Fingerabdrücke hoch Drei",
         "titleen":"Episode 066",
         "description":"Kogoro, Ran und Conan werden zu einer Grillparty bei dem Oberinspektor der Ermittlungsbehörde, Herrn Teraoka und seiner Frau Misako eingeladen. Teraokas Handy klingelt. Er wird von einem Gangster zum Hafen bestellt. Kogoro, Ran und Conan, die ihm gefolgt sind, finden den Gangster erschossen mit einer Pistole in der Hand am Boden liegen. Neben der Leiche steht der Oberinspektor. War es Notwehr, ein Unfall oder Mord? Wie immer gibt es nur eine Wahrheit und Conan findet sie.",
         "links":[
                {
                        "hoster":"YouTube",
                        "part":1,
                        "link":"=YNoDLX-T1Uw"
                },{
                        "hoster":"YouTube",
                        "part":2,
                        "link":"=safTq-sHq8c"
                },{
                        "hoster":"MyVideo",
                        "part":1,
                        "link":"6254398/Detektiv_Conan_Folge_66_1_3"
                },{
                        "hoster":"MyVideo",
                        "part":2,
                        "link":"6254468/Detektiv_Conan_Folge_66_2_3"
                },{
                        "hoster":"MyVideo",
                        "part":3,
                        "link":"6254522/Detektiv_Conan_Folge_66_3_3"
                }
       ]
}