{ 
         "titlede":"Die Natur will nur spielen",
         "titleen":"Nature&#039;s Game Show",
         "description":"Camden wird von einer Serie gewaltiger Tornados heimgesucht, die die gesamte Einwohnerschaft in Panik versetzt. Insbesondere die Bewohner des Trailerparks zeigen angesichts der Naturkatastrophe alsbald einige Verhaltensauffälligkeiten, da sie das tobende Wetter für ein Zeichen Gottes halten. So stehen zum Beispiel Catalina und Patty in einem herbei gewehten Boot, das sie für eine vom Allmächtigen geschickte Arche halten. Randy wird auf das Dach des Motels geweht und glaubt fortan, er sei ein unverwundbarer Superheld, der fliegen kann und den Auftrag hat, die Menschheit zu retten. Nur Earl ist der Einzige, der in dem ganzen Tohuwabohu versucht, einen klaren Kopf zu behalten. Doch ausgerechnet er erhält durch die Tornados tatsächlich ein Zeichen. Denn er wird daran erinnert, dass er die blaue Tür seines &#039;El Camino&#039; auch einem Wirbelsturm verdankt und es nun Zeit wird, diese ihrem rechtmäßigen Besitzer zwecks Wiedergutmachung zurückzubringen...",
         "links":[
                {
                        "hoster":"PutLocker",
                        "part":1,
                        "link":"44694775582afc08"
                },{
                        "hoster":"Sockshare",
                        "part":1,
                        "link":"417E2992EF122BE6"
                }
       ]
}