{ 
         "titlede":"Mr. Monk in Las Vegas",
         "titleen":"Mr. Monk Goes to Vegas",
         "description":"Mitten in der Nacht erhält Monk einen Anruf von einem betrunkenen Lt. Stottlemeyer. Dieser weilt gemeinsam mit Disher bei einem Junggesellenabschied eines Kollegen in Las Vegas. Er bittet Monk, sofort zu ihm zu fliegen. Die Frau eines Casinobesitzers ist tot. Angeblich ein Unfall, doch Stottlemeyer glaubt an Mord. Als Monk tags darauf in der bunten Spielerstadt ankommt, kann sich der verkaterte Lieutenant leider an nichts mehr erinnern. Monk und Nathalie gehen auf Spurensuche.",
         "links":[
                {
                        "hoster":"PutLocker",
                        "part":1,
                        "link":"4FDDF2372F1DF4E4"
                }
       ]
}