{ 
         "titlede":"Freitag der Dreizehnte",
         "titleen":"To Tell a Mortal",
         "description":"Nur an einem Freitag dem Dreizehnten dürfen Hexen ihren Freunden die Wahrheit über ihr Dasein offenbaren, denn danach vergessen die Außenstehenden alles wieder. Sabrina wird allerdings von ihren Tanten eindringlich davor gewarnt. Trotzdem vertraut Sabrina Valerie und Harvey ihr Geheimnis an. Das hat schlimme Folgen.",
         "links":[
                {
                        "hoster":"PutLocker",
                        "part":1,
                        "link":"0785DCD95C18649A"
                },{
                        "hoster":"Sockshare",
                        "part":1,
                        "link":"33E7B45D02899AC1"
                },{
                        "hoster":"RapidVideo",
                        "part":1,
                        "link":"nx4i2d08"
                }
       ]
}