{ 
         "titlede":"Gauner und Fallen",
         "titleen":"The Runaway",
         "description":"Toph und Sokka ergaunern sich mit faulen Tricks ein paar Silbermünzen. Einmal auf den Geschmack gekommen, wollen sie mit ihrer Masche gar nicht mehr aufhören. Sokka kauft sich vom Gewinn einen Botenfalken. Katara ist über die Geldgier ihrer Freunde entsetzt und gerät mit ihnen in Streit. Toph und Sokka sind nicht bereit, klein beizugeben - doch als ihre Gaunereien auffliegen, geraten die beiden in ernste Schwierigkeiten. Aang entgeht derweil nur knapp einem Angriff des unheimlichen Fremden, der die Gruppe seit einiger Zeit verfolgt...",
         "links":[
                {
                        "hoster":"PutLocker",
                        "part":1,
                        "link":"2A9890C821CE82AE"
                },{
                        "hoster":"RapidVideo",
                        "part":1,
                        "link":"ivr4fxac"
                }
       ]
}