{ 
         "titlede":"Gelandet!",
         "titleen":"Arrival",
         "description":"Der gewaltige und zerstörerische Meteoritenschauer ist vorbei, und Clark findet sich plötzlich in einer riesigen Eiswüste wieder, wo sich ein mächtiges Gebäude vor ihm auftürmt. Wie ihm die Stimme Jor-Els erklärt, handelt es sich dabei um sein zukünftiges Zuhause - die Festung der Einsamkeit, in der er auf seine künftige Rolle als Weltenbeherrscher vorbereitet wird. Als Clark jedoch seine Freundin Chloe, die mit ihm gemeinsam durch den gewaltigen Energiestrahl ins ewige Eis transportiert wurde, in der Eisfestung entdeckt, bittet Clark Jor-El, sich zunächst um Chloe kümmern zu dürfen. In Smallville herrscht unterdessen Chaos. Etliche Häuser sind dem Erdboden gleich gemacht worden und im Krankenhaus herrscht Hochbetrieb. Auch Clarks Mutter zählt zu den zahlreichen Verwundeten. Lana, die während des Meteoritenschauers mit dem LuthorCorp-Hubschrauber abgestürzt ist, vergisst schlagartig all ihre Schmerzen, als sie Zeugin wird, wie aus dem bedrohlichen Raumschiff, das ganz in der Nähe gelandet ist, zwei Furcht erregende Gestalten aussteigen. Dabei handelt es sich um die Kryptonier Aethyr und Nam-Ek, die sich rücksichtlos auf der Suche nach Kal-El den Weg durch die Menschenmenge bahnen. Clark erfährt, dass die beiden Wesen nach ihm suchen und es gelingt ihm, die beiden unschädlich zu machen. Doch noch ist die Gefahr nicht gebannt, denn eine weitere bösartige Kreatur befindet sich im Raumschiff...",
         "links":[
                {
                        "hoster":"PutLocker",
                        "part":1,
                        "link":"76A53ACEB2EB14EA"
                }
       ]
}